ufesp/__init__.py
ufesp/paths.py
ufesp/read_data.py
ufesp/data/ufesp.csv
ufesp-0.1.1.dist-info/METADATA
ufesp-0.1.1.dist-info/WHEEL
ufesp-0.1.1.dist-info/licenses/LICENSE
ufesp-0.1.1.dist-info/RECORD
