Metadata-Version: 2.4
Name: ufesp
Version: 0.1.1
Summary: Série Temporal da Unidade Fiscal do Estado de São Paulo e métodos para recuperar informações da UFESP
Author-email: Michel Metran <michelmetran@gmail.com>
License-File: LICENSE
Keywords: correção monetária,finance,multas,python,tjsp,ufesp
Classifier: Intended Audience :: Developers
Classifier: License :: OSI Approved :: MIT License
Classifier: Natural Language :: Portuguese
Classifier: Operating System :: OS Independent
Classifier: Programming Language :: Python :: 3
Requires-Python: >=3.11
Requires-Dist: lxml>=6.0.0
Requires-Dist: pandas>=2.0.0
